{
 "PRed":[
  {
   "data":{
    "bot_rerun":false,
    "migrator_name":"Version",
    "migrator_version":0,
    "version":"2.3.2"
   },
   "keys":[
    "bot_rerun",
    "migrator_name",
    "migrator_version",
    "version"
   ]
  },
  {
   "PR":{
    "__lazy_json__":"pr_json/199906836.json"
   },
   "data":{
    "bot_rerun":false,
    "migrator_name":"Noarch",
    "migrator_version":0
   },
   "keys":[
    "bot_rerun",
    "migrator_name",
    "migrator_version"
   ]
  },
  {
   "PR":{
    "__lazy_json__":"pr_json/244281946.json"
   },
   "data":{
    "bot_rerun":false,
    "migrator_name":"Version",
    "migrator_version":0,
    "version":"2.4.0"
   },
   "keys":[
    "bot_rerun",
    "migrator_name",
    "migrator_version",
    "version"
   ]
  },
  {
   "PR":{
    "__lazy_json__":"pr_json/257769011.json"
   },
   "data":{
    "bot_rerun":false,
    "migrator_name":"Version",
    "migrator_version":0,
    "version":"2.4.2"
   },
   "keys":[
    "bot_rerun",
    "migrator_name",
    "migrator_version",
    "version"
   ]
  },
  {
   "PR":{
    "__lazy_json__":"pr_json/283618954.json"
   },
   "data":{
    "bot_rerun":false,
    "migrator_name":"Version",
    "migrator_version":0,
    "version":"2.5.0"
   },
   "keys":[
    "bot_rerun",
    "migrator_name",
    "migrator_version",
    "version"
   ]
  },
  {
   "PR":{
    "__lazy_json__":"pr_json/307404216.json"
   },
   "data":{
    "bot_rerun":false,
    "migrator_name":"Version",
    "migrator_version":0,
    "version":"2.5.1"
   },
   "keys":[
    "bot_rerun",
    "migrator_name",
    "migrator_version",
    "version"
   ]
  },
  {
   "PR":{
    "__lazy_json__":"pr_json/322776036.json"
   },
   "data":{
    "bot_rerun":false,
    "migrator_name":"Version",
    "migrator_version":0,
    "version":"2.5.2"
   },
   "keys":[
    "bot_rerun",
    "migrator_name",
    "migrator_version",
    "version"
   ]
  }
 ],
 "bad":false,
 "conda-forge.yml":{},
 "feedstock_name":"amqp",
 "hash_type":"sha256",
 "meta_yaml":{
  "about":{
   "dev_url":"http://github.com/celery/py-amqp/",
   "doc_url":"https://amqp.readthedocs.io/",
   "home":"http://github.com/celery/py-amqp",
   "license":"BSD 3-clause",
   "license_family":"BSD",
   "license_file":"LICENSE",
   "summary":"Low-level AMQP client for Python (fork of amqplib)"
  },
  "build":{
   "noarch":"python",
   "number":"0",
   "script":"-m pip install . --no-deps -vv"
  },
  "extra":{
   "recipe-maintainers":[
    "anguslees",
    "kwilcox",
    "wseaton",
    "frol",
    "anguslees",
    "kwilcox",
    "wseaton",
    "frol",
    "anguslees",
    "kwilcox",
    "wseaton",
    "frol"
   ]
  },
  "package":{
   "name":"amqp",
   "version":"2.5.2"
  },
  "requirements":{
   "build":[
    "python",
    "pip",
    "python",
    "pip",
    "python",
    "pip"
   ],
   "run":[
    "python",
    "vine >=1.1.3",
    "python",
    "vine >=1.1.3",
    "python",
    "vine >=1.1.3"
   ]
  },
  "source":{
   "fn":"amqp-2.5.2.tar.gz",
   "sha256":"77f1aef9410698d20eaeac5b73a87817365f457a507d82edf292e12cbb83b08d",
   "url":"https://pypi.io/packages/source/a/amqp/amqp-2.5.2.tar.gz"
  },
  "test":{
   "imports":[
    "amqp",
    "amqp",
    "amqp"
   ]
  }
 },
 "name":"amqp",
 "new_version":"2.5.2",
 "pinning_version":"2019.09.27",
 "raw_meta_yaml":"{% set name = \"amqp\" %}\n{% set version = \"2.5.2\" %}\n\npackage:\n    name: {{ name|lower }}\n    version: {{ version }}\n\nsource:\n    fn: {{ name }}-{{ version }}.tar.gz\n    url: https://pypi.io/packages/source/{{ name[0] }}/{{ name }}/{{ name }}-{{ version }}.tar.gz\n    sha256: 77f1aef9410698d20eaeac5b73a87817365f457a507d82edf292e12cbb83b08d\n\nbuild:\n    noarch: python\n    number: 0\n    script: {{ PYTHON }} -m pip install . --no-deps -vv\n\nrequirements:\n    build:\n        - python\n        - pip\n    run:\n        - python\n        - vine >=1.1.3\n\ntest:\n    imports:\n        - amqp\n\nabout:\n    home: http://github.com/celery/py-amqp\n    license: BSD 3-clause\n    license_family: BSD\n    license_file: LICENSE\n    summary: Low-level AMQP client for Python (fork of amqplib)\n    doc_url: https://amqp.readthedocs.io/\n    dev_url: http://github.com/celery/py-amqp/\n\nextra:\n    recipe-maintainers:\n        - anguslees\n        - kwilcox\n        - wseaton\n        - frol\n",
 "req":{
  "__set__":true,
  "elements":[
   "pip",
   "python",
   "vine"
  ]
 },
 "requirements":{
  "build":{
   "__set__":true,
   "elements":[
    "pip",
    "python"
   ]
  },
  "host":{
   "__set__":true,
   "elements":[]
  },
  "run":{
   "__set__":true,
   "elements":[
    "python",
    "vine"
   ]
  },
  "test":{
   "__set__":true,
   "elements":[]
  }
 },
 "smithy_version":"3.4.8",
 "strong_exports":false,
 "total_requirements":{
  "build":{
   "__set__":true,
   "elements":[
    "pip",
    "python"
   ]
  },
  "host":{
   "__set__":true,
   "elements":[]
  },
  "run":{
   "__set__":true,
   "elements":[
    "python",
    "vine >=1.1.3"
   ]
  },
  "test":{
   "__set__":true,
   "elements":[]
  }
 },
 "url":"https://pypi.io/packages/source/a/amqp/amqp-2.5.1.tar.gz",
 "version":"2.5.2"
}