{
 "PRed":[
  {
   "PR":{
    "__lazy_json__":"pr_json/408261633.json"
   },
   "data":{
    "bot_rerun":false,
    "migrator_name":"Version",
    "migrator_version":0,
    "version":"0.1.1"
   },
   "keys":[
    "bot_rerun",
    "migrator_name",
    "migrator_version",
    "version"
   ]
  }
 ],
 "bad":false,
 "conda-forge.yml":{},
 "feedstock_name":"jupyterlab_pygments",
 "hash_type":"sha256",
 "meta_yaml":{
  "about":{
   "description":"The goal is to enable the use of JupyterLab's themes with pygments-generated HTML.\n",
   "dev_url":"https://github.com/JupyterLab/jupyterlab_pygments",
   "home":"http://github.com/JupyterLab/jupyterlab_pygments",
   "license":"BSD-3-Clause",
   "license_family":"BSD",
   "license_file":"LICENSE",
   "summary":"Pygments syntax coloring scheme making use of the JupyterLab CSS variables"
  },
  "build":{
   "noarch":"python",
   "number":"0",
   "script":" -m pip install . --no-deps --ignore-installed --no-cache-dir -vvv"
  },
  "extra":{
   "recipe-maintainers":[
    "SylvainCorlay",
    "maartenbreddels",
    "SylvainCorlay",
    "maartenbreddels",
    "SylvainCorlay",
    "maartenbreddels"
   ]
  },
  "package":{
   "name":"jupyterlab_pygments",
   "version":"0.1.1"
  },
  "requirements":{
   "host":[
    "python",
    "pip",
    "python",
    "pip",
    "python",
    "pip"
   ],
   "run":[
    "python",
    "pygments >=2.4.1,<3",
    "python",
    "pygments >=2.4.1,<3",
    "python",
    "pygments >=2.4.1,<3"
   ]
  },
  "source":{
   "sha256":"19a0ccde7daddec638363cd3d60b63a4f6544c9181d65253317b2fb492a797b9",
   "url":"https://pypi.io/packages/source/j/jupyterlab_pygments/jupyterlab_pygments-0.1.1.tar.gz"
  },
  "test":{
   "imports":[
    "jupyterlab_pygments",
    "jupyterlab_pygments",
    "jupyterlab_pygments"
   ]
  }
 },
 "name":"jupyterlab_pygments",
 "new_version":"0.1.1",
 "new_version_attempts":{
  "0.1.1":1
 },
 "new_version_errors":{},
 "pinning_version":"2020.04.23.22.05.54",
 "raw_meta_yaml":"{% set name = \"jupyterlab_pygments\" %}\n{% set version = \"0.1.1\" %}\n\npackage:\n  name: {{ name|lower }}\n  version: {{ version }}\n\nsource:\n  url: https://pypi.io/packages/source/{{ name[0] }}/{{ name }}/{{ name }}-{{ version }}.tar.gz\n  sha256: 19a0ccde7daddec638363cd3d60b63a4f6544c9181d65253317b2fb492a797b9\n\nbuild:\n  number: 0\n  noarch: python\n  script: \"{{ PYTHON }} -m pip install . --no-deps --ignore-installed --no-cache-dir -vvv\"\n\nrequirements:\n  host:\n    - python\n    - pip\n  run:\n    - python\n    - pygments >=2.4.1,<3\n\ntest:\n  imports:\n    - jupyterlab_pygments\n\nabout:\n  home: http://github.com/JupyterLab/jupyterlab_pygments\n  license: BSD-3-Clause\n  license_family: BSD\n  license_file: LICENSE\n  summary: 'Pygments syntax coloring scheme making use of the JupyterLab CSS variables'\n  description: |\n      The goal is to enable the use of JupyterLab's themes with pygments-generated HTML.\n  dev_url: https://github.com/JupyterLab/jupyterlab_pygments\n\nextra:\n  recipe-maintainers:\n    - SylvainCorlay\n    - maartenbreddels\n",
 "req":{
  "__set__":true,
  "elements":[
   "pip",
   "pygments",
   "python"
  ]
 },
 "requirements":{
  "build":{
   "__set__":true,
   "elements":[]
  },
  "host":{
   "__set__":true,
   "elements":[
    "pip",
    "python"
   ]
  },
  "run":{
   "__set__":true,
   "elements":[
    "pygments",
    "python"
   ]
  },
  "test":{
   "__set__":true,
   "elements":[]
  }
 },
 "smithy_version":"No azure token. Create a token and\nput it in ~/.conda-smithy/azure.token\n3.6.17",
 "strong_exports":false,
 "total_requirements":{
  "build":{
   "__set__":true,
   "elements":[]
  },
  "host":{
   "__set__":true,
   "elements":[
    "pip",
    "python"
   ]
  },
  "run":{
   "__set__":true,
   "elements":[
    "pygments >=2.4.1,<3",
    "python"
   ]
  },
  "test":{
   "__set__":true,
   "elements":[]
  }
 },
 "url":"https://pypi.io/packages/source/j/jupyterlab_pygments/jupyterlab_pygments-0.1.0.tar.gz",
 "version":"0.1.1"
}