{
 "PRed":[
  {
   "PR":{
    "__lazy_json__":"pr_json/230850620.json"
   },
   "data":{
    "bot_rerun":false,
    "migrator_name":"CompilerRebuild",
    "migrator_version":1,
    "name":"Python 3.7, GCC 7, R 3.5.1, openBLAS 0.3.2"
   },
   "keys":[
    "bot_rerun",
    "migrator_name",
    "migrator_version",
    "name"
   ]
  },
  {
   "PR":{
    "__lazy_json__":"pr_json/299557343.json"
   },
   "data":{
    "bot_rerun":false,
    "migrator_name":"RBaseRebuild",
    "migrator_version":0,
    "name":"r-base-3.6.1"
   },
   "keys":[
    "bot_rerun",
    "migrator_name",
    "migrator_version",
    "name"
   ]
  },
  {
   "PR":{
    "__lazy_json__":"pr_json/342650590.json"
   },
   "data":{
    "bot_rerun":false,
    "migrator_name":"Version",
    "migrator_version":0,
    "version":"2.2_0"
   },
   "keys":[
    "bot_rerun",
    "migrator_name",
    "migrator_version",
    "version"
   ]
  },
  {
   "PR":{
    "__lazy_json__":"pr_json/413648363.json"
   },
   "data":{
    "bot_rerun":false,
    "migrator_name":"MigrationYaml",
    "migrator_object_version":2,
    "migrator_version":0,
    "name":"r400"
   },
   "keys":[
    "bot_rerun",
    "migrator_name",
    "migrator_object_version",
    "migrator_version",
    "name"
   ]
  }
 ],
 "bad":false,
 "conda-forge.yml":{
  "bot":{
   "automerge":true
  },
  "provider":{
   "win":"azure"
  }
 },
 "feedstock_name":"r-pvclust",
 "hash_type":"sha256",
 "meta_yaml":{
  "about":{
   "home":"http://stat.sys.i.kyoto-u.ac.jp/prog/pvclust/",
   "license":"GPL-2",
   "license_family":"GPL",
   "license_file":[
    "/lib/R/share/licenses/GPL-2",
    "/lib/R/share/licenses/GPL-2",
    "/lib/R/share/licenses/GPL-2"
   ],
   "summary":"An implementation of multiscale bootstrap resampling for assessing the uncertainty in hierarchical cluster analysis. It provides AU (approximately unbiased) p-value as well as BP (bootstrap probability) value for each cluster in a dendrogram."
  },
  "build":{
   "noarch":"generic",
   "number":"1",
   "rpaths":[
    "lib/R/lib/",
    "lib/",
    "lib/R/lib/",
    "lib/",
    "lib/R/lib/",
    "lib/"
   ]
  },
  "extra":{
   "recipe-maintainers":[
    "conda-forge/r",
    "sebastian-luna-valero",
    "conda-forge/r",
    "sebastian-luna-valero",
    "conda-forge/r",
    "sebastian-luna-valero"
   ]
  },
  "package":{
   "name":"r-pvclust",
   "version":"2.2_0"
  },
  "requirements":{
   "host":[
    "r-base",
    "r-base",
    "r-base"
   ],
   "run":[
    "r-base",
    "r-base",
    "r-base"
   ]
  },
  "source":{
   "fn":"pvclust_2.2-0.tar.gz",
   "sha256":"7892853bacd413b5a921006429641ad308a344ca171b3081c15e4c522a8b0201",
   "url":[
    "https://cran.r-project.org/src/contrib/pvclust_2.2-0.tar.gz",
    "https://cran.r-project.org/src/contrib/Archive/pvclust/pvclust_2.2-0.tar.gz",
    "https://cran.r-project.org/src/contrib/pvclust_2.2-0.tar.gz",
    "https://cran.r-project.org/src/contrib/Archive/pvclust/pvclust_2.2-0.tar.gz",
    "https://cran.r-project.org/src/contrib/pvclust_2.2-0.tar.gz",
    "https://cran.r-project.org/src/contrib/Archive/pvclust/pvclust_2.2-0.tar.gz"
   ]
  },
  "test":{
   "commands":[
    "\"%R%\" -e \"library('pvclust')\"",
    "$R -e \"library('pvclust')\"",
    "$R -e \"library('pvclust')\""
   ]
  }
 },
 "name":"r-pvclust",
 "new_version":"2.2_0",
 "pinning_version":"2020.05.04.19.59.17",
 "raw_meta_yaml":"{% set version = \"2.2-0\" %}\n\n{% set posix = 'm2-' if win else '' %}\n{% set native = 'm2w64-' if win else '' %}\n\npackage:\n  name: r-pvclust\n  version: {{ version|replace(\"-\", \"_\") }}\n\nsource:\n  fn: pvclust_{{ version }}.tar.gz\n  url:\n    - https://cran.r-project.org/src/contrib/pvclust_{{ version }}.tar.gz\n    - https://cran.r-project.org/src/contrib/Archive/pvclust/pvclust_{{ version }}.tar.gz\n  sha256: 7892853bacd413b5a921006429641ad308a344ca171b3081c15e4c522a8b0201\n\nbuild:\n  noarch: generic\n  number: 1\n\n  rpaths:\n    - lib/R/lib/\n    - lib/\n\nrequirements:\n  host:\n    - r-base\n  run:\n    - r-base\n\ntest:\n  commands:\n    - $R -e \"library('pvclust')\"  # [not win]\n    - \"\\\"%R%\\\" -e \\\"library('pvclust')\\\"\"  # [win]\n\nabout:\n  home: http://stat.sys.i.kyoto-u.ac.jp/prog/pvclust/\n  license: GPL-2\n  summary: An implementation of multiscale bootstrap resampling for assessing the uncertainty\n    in hierarchical cluster analysis. It provides AU (approximately unbiased) p-value\n    as well as BP (bootstrap probability) value for each cluster in a dendrogram.\n  license_family: GPL\n  license_file:\n    - '{{ environ[\"PREFIX\"] }}/lib/R/share/licenses/GPL-2'\n\nextra:\n  recipe-maintainers:\n    - conda-forge/r\n    - sebastian-luna-valero\n",
 "req":{
  "__set__":true,
  "elements":[
   "r-base"
  ]
 },
 "requirements":{
  "build":{
   "__set__":true,
   "elements":[]
  },
  "host":{
   "__set__":true,
   "elements":[
    "r-base"
   ]
  },
  "run":{
   "__set__":true,
   "elements":[
    "r-base"
   ]
  },
  "test":{
   "__set__":true,
   "elements":[]
  }
 },
 "smithy_version":"No azure token. Create a token and\nput it in ~/.conda-smithy/azure.token\n3.7.0\n",
 "strong_exports":false,
 "total_requirements":{
  "build":{
   "__set__":true,
   "elements":[]
  },
  "host":{
   "__set__":true,
   "elements":[
    "r-base"
   ]
  },
  "run":{
   "__set__":true,
   "elements":[
    "r-base"
   ]
  },
  "test":{
   "__set__":true,
   "elements":[]
  }
 },
 "url":[
  "https://cran.r-project.org/src/contrib/pvclust_2.0-0.tar.gz",
  "https://cran.r-project.org/src/contrib/Archive/pvclust/pvclust_2.0-0.tar.gz",
  "https://cran.r-project.org/src/contrib/pvclust_2.0-0.tar.gz",
  "https://cran.r-project.org/src/contrib/Archive/pvclust/pvclust_2.0-0.tar.gz",
  "https://cran.r-project.org/src/contrib/pvclust_2.0-0.tar.gz",
  "https://cran.r-project.org/src/contrib/Archive/pvclust/pvclust_2.0-0.tar.gz"
 ],
 "version":"2.2_0"
}