{
 "PRed":[
  {
   "PR":{
    "__lazy_json__":"pr_json/297619831.json"
   },
   "data":{
    "bot_rerun":false,
    "migrator_name":"Version",
    "migrator_version":0,
    "version":"1.13.0"
   },
   "keys":[
    "bot_rerun",
    "migrator_name",
    "migrator_version",
    "version"
   ]
  },
  {
   "PR":{
    "__lazy_json__":"pr_json/328470233.json"
   },
   "data":{
    "bot_rerun":false,
    "migrator_name":"Version",
    "migrator_version":0,
    "version":"2.0"
   },
   "keys":[
    "bot_rerun",
    "migrator_name",
    "migrator_version",
    "version"
   ]
  },
  {
   "PR":{
    "__lazy_json__":"pr_json/339410839.json"
   },
   "data":{
    "bot_rerun":false,
    "migrator_name":"MigrationYaml",
    "migrator_object_version":1,
    "migrator_version":0,
    "name":"python38"
   },
   "keys":[
    "bot_rerun",
    "migrator_name",
    "migrator_object_version",
    "migrator_version",
    "name"
   ]
  },
  {
   "PR":{
    "__lazy_json__":"pr_json/369336124.json"
   },
   "data":{
    "bot_rerun":false,
    "migrator_name":"Version",
    "migrator_version":0,
    "version":"2.1.0"
   },
   "keys":[
    "bot_rerun",
    "migrator_name",
    "migrator_version",
    "version"
   ]
  },
  {
   "PR":{
    "__lazy_json__":"pr_json/1ff69f09-d58c-40a4-96f8-485be4200d28.json"
   },
   "data":{
    "bot_rerun":false,
    "migrator_name":"MigrationYaml",
    "migrator_object_version":1,
    "migrator_version":0,
    "name":"pypy"
   },
   "keys":[
    "bot_rerun",
    "migrator_name",
    "migrator_object_version",
    "migrator_version",
    "name"
   ]
  }
 ],
 "bad":false,
 "conda-forge.yml":{},
 "feedstock_name":"tf_object_detection",
 "hash_type":"sha256",
 "meta_yaml":{
  "about":{
   "description":"The TensorFlow Object Detection API is an open source\nframework built on top of TensorFlow that makes it easy\nto construct, train and deploy object detection models\n",
   "home":"https://github.com/tensorflow/models/tree/master/research/object_detection",
   "license":"Apache 2.0",
   "license_file":"LICENSE",
   "summary":"As an open source framework to to construct, train and deploy object detection models"
  },
  "build":{
   "number":"1",
   "skip":true
  },
  "extra":{
   "recipe-maintainers":[
    "adbeda",
    "oblute",
    "rluria14",
    "adbeda",
    "oblute",
    "rluria14",
    "adbeda",
    "oblute",
    "rluria14"
   ]
  },
  "package":{
   "name":"tf_object_detection",
   "version":"0.01"
  },
  "requirements":{
   "build":[
    "python",
    "setuptools",
    "python",
    "setuptools",
    "python",
    "setuptools"
   ],
   "host":[
    "python",
    "pip",
    "protobuf",
    "python",
    "pip",
    "protobuf",
    "python",
    "pip",
    "protobuf"
   ],
   "run":[
    "python",
    "tensorflow >=1.12.0",
    "numpy >=1.16.1",
    "protobuf >=3.0.0",
    "python",
    "tensorflow >=1.12.0",
    "numpy >=1.16.1",
    "protobuf >=3.0.0",
    "python",
    "tensorflow >=1.12.0",
    "numpy >=1.16.1",
    "protobuf >=3.0.0"
   ]
  },
  "source":{
   "sha256":"9e762d306888b2bf611a45153a30062d2f40f3afa677df9a6e93efe7bd483832",
   "url":"https://github.com/tensorflow/models/archive/v1.13.0.tar.gz"
  },
  "test":{
   "imports":null,
   "requires":[
    "tensorflow",
    "cython",
    "tensorflow",
    "cython",
    "tensorflow",
    "cython"
   ]
  }
 },
 "name":"tf_object_detection",
 "new_version":"2.2.0",
 "new_version_attempts":{
  "2.2.0":137
 },
 "new_version_errors":{
  "2.2.0":"The recipe did not change in the version migration, a URL did not hash, or there is jinja2 syntax the bot cannot handle!\n\nPlease check the URLs in your recipe with version '2.2.0' to make sure they exist!\n\nWe also found the following errors:\n\n - recipe did not appear to change even though the bot said it should have\n"
 },
 "pinning_version":"2020.03.30",
 "raw_meta_yaml":"{% set name = \"tf_object_detection\" %}\n{% set version = \"0.01\" %}\n\npackage:\n  name: {{ name|lower }}\n  version: {{ version }}\nsource:\n  url: https://github.com/tensorflow/models/archive/v1.13.0.tar.gz\n  sha256: 9e762d306888b2bf611a45153a30062d2f40f3afa677df9a6e93efe7bd483832\n\nbuild:\n  number: 1\n  skip: True  # [win]  # Skip all windows for now due to numpy/scipy version pinning issues\n\n\nrequirements:\n  build:\n    - python\n    - setuptools\n  host:\n    - python\n    - pip\n    - protobuf\n  run:\n    - python\n    - tensorflow >=1.12.0\n    - numpy >=1.16.1\n    - protobuf >=3.0.0\n\n\ntest:\n  imports:\n    # From tensorflow-feedstock:\n    # \"Skip the import test on Linux as wheel file require a more recent\n    # version of GLIBC++ than the VM used to build and test package.\n    # Also skip on OSX due to OSX version requirements, see\n    # https://github.com/conda-forge/tensorflow-feedstock/pull/62\"\n    - tf_object_detection  # [win]\n  requires:\n    - tensorflow\n    - cython\n\nabout:\n  home: https://github.com/tensorflow/models/tree/master/research/object_detection\n  license: Apache 2.0\n  license_file: LICENSE\n  summary: 'As an open source framework to to construct, train and deploy object detection models'\n\n  description: |\n    The TensorFlow Object Detection API is an open source\n    framework built on top of TensorFlow that makes it easy\n    to construct, train and deploy object detection models\n\n\nextra:\n  recipe-maintainers:\n    - adbeda\n    - oblute\n    - rluria14\n",
 "req":{
  "__set__":true,
  "elements":[
   "numpy",
   "pip",
   "protobuf",
   "python",
   "setuptools",
   "tensorflow"
  ]
 },
 "requirements":{
  "build":{
   "__set__":true,
   "elements":[
    "python",
    "setuptools"
   ]
  },
  "host":{
   "__set__":true,
   "elements":[
    "pip",
    "protobuf",
    "python"
   ]
  },
  "run":{
   "__set__":true,
   "elements":[
    "numpy",
    "protobuf",
    "python",
    "tensorflow"
   ]
  },
  "test":{
   "__set__":true,
   "elements":[
    "cython",
    "tensorflow"
   ]
  }
 },
 "smithy_version":"No azure token. Create a token and\nput it in ~/.conda-smithy/azure.token\n3.6.15",
 "strong_exports":false,
 "total_requirements":{
  "build":{
   "__set__":true,
   "elements":[
    "python",
    "setuptools"
   ]
  },
  "host":{
   "__set__":true,
   "elements":[
    "pip",
    "protobuf",
    "python"
   ]
  },
  "run":{
   "__set__":true,
   "elements":[
    "numpy >=1.16.1",
    "protobuf >=3.0.0",
    "python",
    "tensorflow >=1.12.0"
   ]
  },
  "test":{
   "__set__":true,
   "elements":[
    "cython",
    "tensorflow"
   ]
  }
 },
 "url":"https://github.com/tensorflow/models/archive/v1.13.0.tar.gz",
 "version":"0.01"
}